gbpclient/__init__.py
gbpclient/gbpshell.py
gbpclient/version.py
gbpclient/common/__init__.py
gbpclient/common/utils.py
gbpclient/gbp/__init__.py
gbpclient/gbp/v2_0/__init__.py
gbpclient/gbp/v2_0/address_scope.py
gbpclient/gbp/v2_0/groupbasedpolicy.py
gbpclient/gbp/v2_0/network.py
gbpclient/gbp/v2_0/port.py
gbpclient/gbp/v2_0/purge.py
gbpclient/gbp/v2_0/router.py
gbpclient/gbp/v2_0/subnet.py
gbpclient/tests/__init__.py
gbpclient/tests/unit/__init__.py
gbpclient/tests/unit/test_address_scope.py
gbpclient/tests/unit/test_cli20.py
gbpclient/tests/unit/test_cli20_apg.py
gbpclient/tests/unit/test_cli20_externalpolicy.py
gbpclient/tests/unit/test_cli20_externalsegment.py
gbpclient/tests/unit/test_cli20_l2policy.py
gbpclient/tests/unit/test_cli20_l3policy.py
gbpclient/tests/unit/test_cli20_natpool.py
gbpclient/tests/unit/test_cli20_networkservicepolicy.py
gbpclient/tests/unit/test_cli20_policyaction.py
gbpclient/tests/unit/test_cli20_policyclassifier.py
gbpclient/tests/unit/test_cli20_policyrule.py
gbpclient/tests/unit/test_cli20_policytarget.py
gbpclient/tests/unit/test_cli20_policytargetgroup.py
gbpclient/tests/unit/test_cli20_purge.py
gbpclient/tests/unit/test_network.py
gbpclient/tests/unit/test_port.py
gbpclient/tests/unit/test_router.py
gbpclient/tests/unit/test_subnet.py
gbpclient/tests/unit/test_utils.py
gbpclient/v2_0/__init__.py
gbpclient/v2_0/client.py
python_group_based_policy_client-14.0.0.dist-info/AUTHORS
python_group_based_policy_client-14.0.0.dist-info/LICENSE
python_group_based_policy_client-14.0.0.dist-info/METADATA
python_group_based_policy_client-14.0.0.dist-info/WHEEL
python_group_based_policy_client-14.0.0.dist-info/entry_points.txt
python_group_based_policy_client-14.0.0.dist-info/pbr.json
python_group_based_policy_client-14.0.0.dist-info/top_level.txt
python_group_based_policy_client-14.0.0.dist-info/RECORD
