Metadata-Version: 2.1
Name: python-group-based-policy-client
Version: 14.0.0
Summary: CLI and Client Library for Group Based Policy
Home-page: http://www.openstack.org/
Author: Group Based Policy
Author-email: openstack-dev@lists.openstack.org
License: UNKNOWN
Platform: UNKNOWN
Classifier: Environment :: OpenStack
Classifier: Intended Audience :: Developers
Classifier: Intended Audience :: Information Technology
Classifier: Intended Audience :: System Administrators
Classifier: License :: OSI Approved :: Apache Software License
Classifier: Operating System :: POSIX :: Linux
Classifier: Programming Language :: Python
Classifier: Programming Language :: Python :: 2
Classifier: Programming Language :: Python :: 2.7
Requires-Dist: oslo.serialization (!=2.19.1,>=2.18.0)
Requires-Dist: oslo.utils (>=3.33.0)
Requires-Dist: pbr (!=2.1.0,>=2.0.0)
Requires-Dist: python-heatclient (>=1.10.0)
Requires-Dist: python-neutronclient (>=6.7.0)
